chuk_sessions/__init__.py
chuk_sessions/api.py
chuk_sessions/enums.py
chuk_sessions/exceptions.py
chuk_sessions/models.py
chuk_sessions/provider_factory.py
chuk_sessions/session_manager.py
chuk_sessions/providers/__init__.py
chuk_sessions/providers/memory.py
chuk_sessions/providers/redis.py
chuk_sessions/utils/__init__.py
chuk_sessions/utils/security/__init__.py
chuk_sessions/utils/security/constants.py
chuk_sessions/utils/security/csrf.py
chuk_sessions/utils/security/session_ids.py
chuk_sessions-0.6.dist-info/licenses/LICENSE
chuk_sessions-0.6.dist-info/METADATA
chuk_sessions-0.6.dist-info/WHEEL
chuk_sessions-0.6.dist-info/top_level.txt
chuk_sessions-0.6.dist-info/RECORD
