Metadata-Version: 2.4
Name: chuk-sessions
Version: 0.6
Summary: CHUK Sessions provides a comprehensive, async-first session management system with automatic expiration, and support for both in-memory and Redis storage backends. Perfect for web applications, MCP servers, API gateways, and microservices that need reliable, scalable session handling.
Requires-Python: >=3.11
License-File: LICENSE
Requires-Dist: csrf>=0.1b1
Requires-Dist: pydantic>=2.10.6
Requires-Dist: pyyaml>=6.0.2
Provides-Extra: redis
Requires-Dist: redis>=6.2.0; extra == "redis"
Provides-Extra: dev
Requires-Dist: pytest>=8.3.5; extra == "dev"
Requires-Dist: pytest-asyncio>=0.26.0; extra == "dev"
Requires-Dist: pytest-cov>=5.0.0; extra == "dev"
Requires-Dist: ruff>=0.4.6; extra == "dev"
Requires-Dist: mypy>=1.0.0; extra == "dev"
Requires-Dist: bandit>=1.7.0; extra == "dev"
Requires-Dist: twine>=5.0.0; extra == "dev"
Requires-Dist: psutil>=7.0.0; extra == "dev"
Provides-Extra: all
Requires-Dist: redis>=6.2.0; extra == "all"
Dynamic: license-file
